piickle/PickleEnum.py
piickle/__init__.py
piickle-1.1.1.dist-info/LICENSE
piickle-1.1.1.dist-info/METADATA
piickle-1.1.1.dist-info/WHEEL
piickle-1.1.1.dist-info/top_level.txt
piickle-1.1.1.dist-info/RECORD
