Metadata-Version: 2.1
Name: piickle
Version: 1.1.1
Summary: The one true Pickler
Home-page: https://github.com/Gusgus01/Pickle
Author: Gus Foley
Author-email: gus.gus.rocks@gmail.com
License: MIT
Platform: UNKNOWN
Requires-Python: >=3
